sonnerrise_core/__init__.py
sonnerrise_core/cli.py
sonnerrise_core/config.py
sonnerrise_core/models.py
sonnerrise_core/database/__init__.py
sonnerrise_core/database/base.py
sonnerrise_core/database/mysql.py
sonnerrise_core/database/registry.py
sonnerrise_core/database/sqlite.py
sonnerrise_core-0.1.0.dist-info/METADATA
sonnerrise_core-0.1.0.dist-info/WHEEL
sonnerrise_core-0.1.0.dist-info/entry_points.txt
sonnerrise_core-0.1.0.dist-info/RECORD
