Metadata-Version: 2.4
Name: sonnerrise-core
Version: 0.1.0
Summary: Core module for Sonnerrise - config loader and database abstraction
Author-email: Konstantin Boyandin <developer@boyandin.com>
License-Expression: MIT
Requires-Python: >=3.11
Requires-Dist: pydantic>=2.0
Requires-Dist: pymysql>=1.1
Requires-Dist: pyyaml>=6.0
Requires-Dist: sqlalchemy>=2.0
Provides-Extra: dev
Requires-Dist: pytest-cov>=4.0; extra == 'dev'
Requires-Dist: pytest>=7.0; extra == 'dev'
